<?xml version = '1.0' encoding = 'UTF-8'?>
<TableProxyOraclev11g class="oracle.dbtools.crest.model.design.storage.oracle.v11g.TableProxyOraclev11g" name="ARTICLES_SUBSCRIBTIONS" id="ED048AE3-229E-D0C9-5A12-87B03D0031F7" directorySegmentName="seg_0">
   <createdBy>Jindra</createdBy>
   <createdTime>2012-03-01 15:41:30 UTC</createdTime>
   <changedBy>Jindra</changedBy>
   <changedTime>2012-03-01 15:41:53 UTC</changedTime>
   <ownerDesignName>EEGTEST</ownerDesignName>
   <logging>YES</logging>
   <partitionedRowMovement>DISABLE</partitionedRowMovement>
   <segment>D980C957-2D0A-ABF7-AF3E-9232DCF36391</segment>
   <tableSpace>99D389EE-5731-85B9-8DB7-8B408D00CFB4</tableSpace>
   <columnProxies>
      <ColumnProxy class="oracle.dbtools.crest.model.design.storage.oracle.v11g.ColumnProxyOraclev11g" name="ARTICLE_ID" id="8C5FD15E-94F6-96A7-30EC-C7B857311265">
         <createdBy>Jindra</createdBy>
         <createdTime>2012-03-01 15:41:32 UTC</createdTime>
         <changedBy>Jindra</changedBy>
         <changedTime>2012-03-01 15:41:32 UTC</changedTime>
         <ownerDesignName>EEGTEST</ownerDesignName>
      </ColumnProxy>
      <ColumnProxy class="oracle.dbtools.crest.model.design.storage.oracle.v11g.ColumnProxyOraclev11g" name="PERSON_ID" id="AE55D9F8-143D-852F-34F5-E8BE2E07BFDE">
         <createdBy>Jindra</createdBy>
         <createdTime>2012-03-01 15:41:32 UTC</createdTime>
         <changedBy>Jindra</changedBy>
         <changedTime>2012-03-01 15:41:32 UTC</changedTime>
         <ownerDesignName>EEGTEST</ownerDesignName>
      </ColumnProxy>
   </columnProxies>
   <foreignKeys>
      <ForeignKey class="oracle.dbtools.crest.model.design.storage.oracle.v10g.FKProxyOraclev10g" name="ARTICLES_SUBSCRIPTIONS_AR_FK1" id="CD7D14CE-21B6-467B-DA8A-346AD0DBF22B">
         <createdBy>Jindra</createdBy>
         <createdTime>2012-03-01 15:41:53 UTC</createdTime>
         <changedBy>Jindra</changedBy>
         <changedTime>2012-03-01 15:41:53 UTC</changedTime>
         <ownerDesignName>EEGTEST</ownerDesignName>
      </ForeignKey>
      <ForeignKey class="oracle.dbtools.crest.model.design.storage.oracle.v10g.FKProxyOraclev10g" name="ARTICLES_SUBSCRIPTIONS_PE_FK1" id="E194D1EE-8F8C-ED8B-DEA8-7FBC6731AF08">
         <createdBy>Jindra</createdBy>
         <createdTime>2012-03-01 15:41:53 UTC</createdTime>
         <changedBy>Jindra</changedBy>
         <changedTime>2012-03-01 15:41:53 UTC</changedTime>
         <ownerDesignName>EEGTEST</ownerDesignName>
      </ForeignKey>
   </foreignKeys>
   <primaryKeys>
      <PrimaryKey class="oracle.dbtools.crest.model.design.storage.oracle.v10g.PKProxyOraclev10g" name="ARTICLES_SUBSCRIBTIONS_PK" id="18A94B98-B7F0-AB4C-D860-AF238B13CF9E">
         <createdBy>Jindra</createdBy>
         <createdTime>2012-03-01 15:41:40 UTC</createdTime>
         <changedBy>Jindra</changedBy>
         <changedTime>2012-03-01 15:41:40 UTC</changedTime>
         <ownerDesignName>EEGTEST</ownerDesignName>
         <indexSort>NO</indexSort>
      </PrimaryKey>
   </primaryKeys>
</TableProxyOraclev11g>